rehydrax/__init__.py
rehydrax/_src/core.py
rehydrax/_src/test_core.py
rehydrax/_src/test_torch2jax.py
rehydrax/_src/torch2jax.py
rehydrax-0.1.0.dist-info/METADATA
rehydrax-0.1.0.dist-info/WHEEL
rehydrax-0.1.0.dist-info/licenses/LICENSE
rehydrax-0.1.0.dist-info/RECORD
