Metadata-Version: 2.4
Name: rehydrax
Version: 0.1.0
Summary: Rehydrax: A utility library to rehydrate stablehlo into JAX.
Project-URL: homepage, https://github.com/armandpicard/rehydrax
Project-URL: repository, https://github.com/armandpicard/rehydrax
Author-email: Armand Picard <armandpicard71@gmail.com>
License: 
License-File: LICENSE
Keywords: jax,stablehlo,torch,xla
Requires-Python: >=3.11
Requires-Dist: jax>=0.4.38
Provides-Extra: dev
Requires-Dist: flax; extra == 'dev'
Requires-Dist: jupyter; extra == 'dev'
Requires-Dist: pip; extra == 'dev'
Requires-Dist: pytest; extra == 'dev'
Requires-Dist: ruff; extra == 'dev'
Requires-Dist: torch-xla[gpu]==2.5.0; extra == 'dev'
Provides-Extra: torch
Requires-Dist: torch-xla>=2.5.0; extra == 'torch'
Requires-Dist: torch>=2.5.0; extra == 'torch'
